MartianWeather/__init__.py
MartianWeather/api.py
MartianWeather/weather.py
MartianWeather-1.0.0.dist-info/LICENSE
MartianWeather-1.0.0.dist-info/METADATA
MartianWeather-1.0.0.dist-info/WHEEL
MartianWeather-1.0.0.dist-info/top_level.txt
MartianWeather-1.0.0.dist-info/RECORD
