Metadata-Version: 2.1
Name: MartianWeather
Version: 1.0.0
Summary: A python wrapper for the Insight: Mars Weather Service API
Home-page: https://gitlab.com/wilmlar/martianweather
Author: William Larsson
License: UNKNOWN
Project-URL: Source, https://gitlab.com/wilmlar/martianweather
Project-URL: Wiki, https://gitlab.com/wilmlar/martianweather/-/wikis/home
Project-URL: Bug Reports, https://gitlab.com/wilmlar/martianweather/-/issues
Keywords: insight,mars,weather,api
Platform: UNKNOWN
Classifier: Programming Language :: Python :: 3
Classifier: License :: OSI Approved :: MIT License
Classifier: Operating System :: OS Independent
Requires-Python: >=3.6
Requires-Dist: requests
